kcb/__main__.py
kcb/kcb.py
kcb/lib/__init__.py
kcb/lib/cd.py
kcb/lib/terminal.py
kcb-0.9.3.dist-info/DESCRIPTION.rst
kcb-0.9.3.dist-info/METADATA
kcb-0.9.3.dist-info/RECORD
kcb-0.9.3.dist-info/WHEEL
kcb-0.9.3.dist-info/entry_points.txt
kcb-0.9.3.dist-info/metadata.json
kcb-0.9.3.dist-info/top_level.txt
