Metadata-Version: 2.0
Name: kcb
Version: 0.9.3
Summary: Execute bash scripts on top of KDEConnect's sshfs mount
Home-page: https://github.com/ReSqAr/kcb
Author: Yasin Zaehringer
Author-email: yasin.zaehringer-kcb@yhjz.de
License: UNKNOWN
Keywords: kdeconnect
Platform: UNKNOWN
Classifier: Programming Language :: Python
Classifier: Programming Language :: Python :: 3
Classifier: Development Status :: 5 - Production/Stable
Classifier: Environment :: Console
Classifier: Intended Audience :: End Users/Desktop
Classifier: License :: OSI Approved :: GNU General Public License v3 (GPLv3)
Classifier: Operating System :: POSIX :: Linux
Classifier: Topic :: System :: Archiving
Classifier: Topic :: Utilities
Requires-Dist: pydbus
Requires-Dist: xdg
